iris_gate-0.2.0.dist-info/licenses/LICENSE
iris_gate-0.2.0.dist-info/licenses/NOTICE
modules/__init__.py
modules/epistemic_map.py
iris_gate-0.2.0.dist-info/METADATA
iris_gate-0.2.0.dist-info/WHEEL
iris_gate-0.2.0.dist-info/entry_points.txt
iris_gate-0.2.0.dist-info/top_level.txt
iris_gate-0.2.0.dist-info/RECORD
