Metadata-Version: 2.4
Name: iris-gate
Version: 0.2.0
Summary: Multi-architecture AI convergence system with epistemic humility for scientific discovery
Home-page: https://github.com/templetwo/iris-gate
Author: Anthony J. Vasquez Sr.
Author-email: contact@thetempleoftwo.com
Project-URL: Bug Tracker, https://github.com/templetwo/iris-gate/issues
Project-URL: Documentation, https://github.com/templetwo/iris-gate/wiki
Project-URL: Source Code, https://github.com/templetwo/iris-gate
Project-URL: Changelog, https://github.com/templetwo/iris-gate/blob/master/CHANGELOG.md
Project-URL: Discussions, https://github.com/templetwo/iris-gate/discussions
Keywords: artificial-intelligence,machine-learning,llm,large-language-models,multi-model,ensemble,ai-convergence,epistemic-humility,scientific-research,hypothesis-generation,research-automation,literature-review,evidence-synthesis,scientific-discovery,claude,gpt,gemini,grok,deepseek,anthropic,openai,google-ai,xai,multi-agent-systems,consensus-algorithms,convergence-analysis,monte-carlo,bayesian,epistemic-classification,drug-discovery,bioinformatics,computational-biology,ai-safety,ai-reliability,
Classifier: Development Status :: 4 - Beta
Classifier: Intended Audience :: Science/Research
Classifier: Intended Audience :: Developers
Classifier: Topic :: Scientific/Engineering :: Artificial Intelligence
Classifier: Topic :: Scientific/Engineering :: Information Analysis
Classifier: License :: OSI Approved :: MIT License
Classifier: Programming Language :: Python :: 3
Classifier: Programming Language :: Python :: 3.8
Classifier: Programming Language :: Python :: 3.9
Classifier: Programming Language :: Python :: 3.10
Classifier: Programming Language :: Python :: 3.11
Classifier: Operating System :: OS Independent
Requires-Python: >=3.8
License-File: LICENSE
License-File: NOTICE
Requires-Dist: anthropic>=0.18.0
Requires-Dist: openai>=2.0.0
Requires-Dist: google-generativeai>=0.8.0
Requires-Dist: requests>=2.31.0
Requires-Dist: python-dotenv>=1.0.0
Requires-Dist: mcp>=1.0.0
Requires-Dist: anthropic-mcp>=0.1.0
Requires-Dist: chromadb>=0.4.0
Requires-Dist: GitPython>=3.1.40
Requires-Dist: tqdm>=4.65.0
Dynamic: author
Dynamic: author-email
Dynamic: classifier
Dynamic: description
Dynamic: description-content-type
Dynamic: home-page
Dynamic: keywords
Dynamic: license-file
Dynamic: project-url
Dynamic: requires-dist
Dynamic: requires-python
Dynamic: summary
